parser/__init__.py
simple_rule_engine-1.0.2.dist-info/LICENSE
simple_rule_engine-1.0.2.dist-info/METADATA
simple_rule_engine-1.0.2.dist-info/WHEEL
simple_rule_engine-1.0.2.dist-info/top_level.txt
simple_rule_engine-1.0.2.dist-info/RECORD
