Metadata-Version: 2.1
Name: simple-rule-engine
Version: 1.0.2
Summary: Lightweight yet flexible Rule Engine Parser that supports declarative specification of complex rules
Home-page: https://github.com/jeyabalajis/simple_rule_engine
Author: Jeyabalaji Subramanian
Author-email: jeyabalaji.subramanian@gmail.com
License: MIT
Keywords: simple rule engine
Platform: UNKNOWN
Classifier: Intended Audience :: Developers
Classifier: License :: OSI Approved :: MIT License
Classifier: Programming Language :: Python :: 3.6
Classifier: Topic :: Software Development :: Libraries :: Python Modules
Classifier: Operating System :: OS Independent
